{
"title": "Newsletter",
"version": "1.10",
"name": "Newsletter",
"description": "Newsletter plugin for ImpressPages.",
"author": "ImpressPages",
    "options": [
        {
            "label": "Require email confirmation",
            "name": "confirmSubscribers",
            "type": "checkbox",
            "hint": "If checked, user will be added to the subscription list only after pressing a confirmation link in his email."
        },
        {
            "label": "Email confirmation subject",
            "name": "confirmEmailSubject",
            "type": "text",
            "default": "Confirm subscription to newsletter"
        },
        {
            "label": "Email confirmation message",
            "name": "confirmEmailMessage",
            "type": "richText",
            "default": "<p>Please click here to confirm the subscription to our newsletter.<br/><br/>{{link}}</p>",
            "hint" : "Use {link} placeholder to place the link"
        },
        {
            "label": "Use following sender e-mail address",
            "name": "fromEmail",
            "type": "text",
            "default": "",
            "note": "Leave empty for default"
        },
        {
            "label": "Send welcome email",
            "name": "sendWelcomeEmail",
            "type": "Checkbox",
            "default": 1
        },
        {
            "label": "Welcome email subject",
            "name": "welcomeEmailSubject",
            "type": "Text",
            "default": "Welcome to our newsletter"
        },
        {
            "label": "Welcome email text",
            "name": "welcomeEmailText",
            "type": "RichText",
            "default": "<p>Welcome to our mailing list. Hope you will enjoy our news. You can unsubscribe at any time by pressing an unsubscribe link at the bottom of every email.</p>"
        }

    ]
}
