{
"title": "Newsletter",
"version": "1.06",
"name": "Newsletter",
"description": "Newsletter plugin for ImpressPages.",
"author": "ImpressPages",
    "options": [
        {
            "label": "Require email confirmation",
            "name": "confirmSubscribers",
            "type": "checkbox",
            "hint": "If checked, user will be added to the subscription list only after pressing a confirmation link in his email."
        },
        {
            "label": "Email confirmation subject",
            "name": "confirmEmailSubject",
            "type": "text",
            "default": "Confirm subscription to newsletter"
        },
        {
            "label": "Email confirmation message",
            "name": "confirmEmailMessage",
            "type": "richText",
            "default": "<p>Please click here to confirm the subscription to our newsletter.<br/><br/>{{link}}</p>",
            "hint" : "Use {{link}} placeholder to place the link"
        },
        {
            "label": "Newsletter admin. items per page",
            "name": "adminPageItems",
            "type": "text",
            "default": "25"
        },
        {
            "label": "From e-mail address",
            "name": "fromEmail",
            "type": "text",
            "default": ""
        }

    ]
}
